AUTHORS.rst
CHANGELOG.md
CONTRIBUTING.rst
LICENSE
MANIFEST.in
README.md
setup.cfg
setup.py
cada_prio/__init__.py
cada_prio/_version.py
cada_prio/cli.py
cada_prio/inspection.py
cada_prio/param_opt.py
cada_prio/predict.py
cada_prio/rest_server.py
cada_prio/server.py
cada_prio/train_model.py
cada_prio.egg-info/PKG-INFO
cada_prio.egg-info/SOURCES.txt
cada_prio.egg-info/dependency_links.txt
cada_prio.egg-info/entry_points.txt
cada_prio.egg-info/not-zip-safe
cada_prio.egg-info/requires.txt
cada_prio.egg-info/top_level.txt
docs/Makefile
docs/authors.rst
docs/cli.rst
docs/conf.py
docs/contributing.rst
docs/history.rst
docs/index.rst
docs/installation.rst
docs/make.bat
requirements/base.txt
requirements/dev.txt
requirements/prod.txt
requirements/test.txt
requirements/tune.txt