Metadata-Version: 2.1
Name: cada-prio
Version: 0.7.0
Summary: Phenotype-based prioritization of variants with CADA
Home-page: https://github.com/bihealth/cada-prio
Author: Manuel Holtgrewe
Author-email: manuel.holtgrewe@bih-charite.de
License: MIT license
Keywords: cada
Classifier: Development Status :: 2 - Pre-Alpha
Classifier: Intended Audience :: Developers
Classifier: License :: OSI Approved :: MIT License
Classifier: Natural Language :: English
Classifier: Programming Language :: Python :: 3
Classifier: Programming Language :: Python :: 3.9
Classifier: Programming Language :: Python :: 3.10
Classifier: Programming Language :: Python :: 3.11
Requires-Python: >=3.6
Provides-Extra: param-tuning
License-File: LICENSE
License-File: AUTHORS.rst
